[{
  "DTSTART;VALUE=DATE": "20220101",
  "DTEND;VALUE=DATE": "20220104",
  "SUMMARY": "🏝元旦放假"
},{
  "DTSTART;VALUE=DATE": "20220129",
  "DTEND;VALUE=DATE": "20220131",
  "SUMMARY": "🚨春节补班"
},{
  "DTSTART;VALUE=DATE": "20220131",
  "DTEND;VALUE=DATE": "20220207",
  "SUMMARY": "🏝春节放假"
},
{
  "DTSTART;VALUE=DATE": "20220402",
  "DTEND;VALUE=DATE": "20220403",
  "SUMMARY": "🚨清明补班"
},{
  "DTSTART;VALUE=DATE": "20220403",
  "DTEND;VALUE=DATE": "20220406",
  "SUMMARY": "🏝清明放假"
},{
  "DTSTART;VALUE=DATE": "20220424",
  "DTEND;VALUE=DATE": "20220425",
  "SUMMARY": "🚨五一补班"
},{
  "DTSTART;VALUE=DATE": "20220430",
  "DTEND;VALUE=DATE": "20220505",
  "SUMMARY": "🏝五一劳动节"
},{
  "DTSTART;VALUE=DATE": "20220507",
  "DTEND;VALUE=DATE": "20220508",
  "SUMMARY": "🚨五一补班"
},{
  "DTSTART;VALUE=DATE": "20220603",
  "DTEND;VALUE=DATE": "20220606",
  "SUMMARY": "🏝端午放假"
},{
  "DTSTART;VALUE=DATE": "20220910",
  "DTEND;VALUE=DATE": "20220913",
  "SUMMARY": "🏝中秋放假"
},{
  "DTSTART;VALUE=DATE": "20221001",
  "DTEND;VALUE=DATE": "20221008",
  "SUMMARY": "🏝十一国庆节"
},{
  "DTSTART;VALUE=DATE": "20221008",
  "DTEND;VALUE=DATE": "20221010",
  "SUMMARY": "🚨十一补班"
}]
